dari/__init__.py
dari/_version.py
dari/client.py
dari_python-0.1.2.dist-info/METADATA
dari_python-0.1.2.dist-info/WHEEL
dari_python-0.1.2.dist-info/RECORD
