Metadata-Version: 2.4
Name: dari-python
Version: 0.1.2
Summary: Tiny Python client for the Dari workflow automation API
Project-URL: Homepage, https://usedari.com
Project-URL: Repository, https://github.com/Mupt/dari-python
Project-URL: Documentation, https://docs.usedari.com
Author-email: Mupt <support@mupt.ai>
License: MIT
Keywords: api,automation,client,dari,workflow
Classifier: Development Status :: 3 - Alpha
Classifier: Intended Audience :: Developers
Classifier: License :: OSI Approved :: MIT License
Classifier: Programming Language :: Python
Classifier: Programming Language :: Python :: 3
Classifier: Programming Language :: Python :: 3.9
Classifier: Programming Language :: Python :: 3.10
Classifier: Programming Language :: Python :: 3.11
Classifier: Programming Language :: Python :: 3.12
Classifier: Topic :: Software Development :: Libraries :: Python Modules
Requires-Python: >=3.9
Requires-Dist: requests>=2.31.0
